mock_data.py
monitor.py
version.py
kubmonitor_cli-0.2.1.dist-info/licenses/LICENSE
kubmonitor_cli-0.2.1.dist-info/METADATA
kubmonitor_cli-0.2.1.dist-info/WHEEL
kubmonitor_cli-0.2.1.dist-info/entry_points.txt
kubmonitor_cli-0.2.1.dist-info/top_level.txt
kubmonitor_cli-0.2.1.dist-info/RECORD
