Metadata-Version: 2.4
Name: kubmonitor-cli
Version: 0.2.1
Summary: A rich CLI Kubernetes monitor
Home-page: https://github.com/yyx/kubmonitor-cli
Author: yyx
Classifier: Programming Language :: Python :: 3
Classifier: License :: OSI Approved :: MIT License
Classifier: Operating System :: OS Independent
Requires-Python: >=3.6
License-File: LICENSE
Requires-Dist: rich
Requires-Dist: psutil
Provides-Extra: dev
Requires-Dist: flake8; extra == "dev"
Dynamic: author
Dynamic: classifier
Dynamic: description
Dynamic: description-content-type
Dynamic: home-page
Dynamic: license-file
Dynamic: provides-extra
Dynamic: requires-dist
Dynamic: requires-python
Dynamic: summary
